[
  {
    "value": "Premier League",
    "categories": ["football-league"],
    "entityRelationships": [
      {
        "relation_type": "in_country",
        "entity": "England"
      }
    ]
  },
  {
    "value": "Championship",
    "categories": ["football-league"],
    "entityRelationships": [
      {
        "relation_type": "in_country",
        "entity": "England"
      }
    ]
  },
  {
    "value": "League One",
    "categories": ["football-league"],
    "entityRelationships": [
      {
        "relation_type": "in_country",
        "entity": "England"
      }
    ]
  },
  {
    "value": "League Two",
    "categories": ["football-league"],
    "entityRelationships": [
      {
        "relation_type": "in_country",
        "entity": "England"
      }
    ]
  },
  {
    "value": "National League",
    "categories": ["football-league"],
    "entityRelationships": [
      {
        "relation_type": "in_country",
        "entity": "England"
      }
    ]
  },
  {
    "value": "La Liga",
    "categories": ["football-league"],
    "entityRelationships": [
      {
        "relation_type": "in_country",
        "entity": "Spain"
      }
    ]
  },
  {
    "value": "Serie A",
    "categories": ["football-league"],
    "entityRelationships": [
      {
        "relation_type": "in_country",
        "entity": "Italy"
      }
    ]
  },
  {
    "value": "Bundesliga",
    "categories": ["football-league"],
    "entityRelationships": [
      {
        "relation_type": "in_country",
        "entity": "Germany"
      }
    ]
  },
  {
    "value": "Ligue 1",
    "categories": ["football-league"],
    "entityRelationships": [
      {
        "relation_type": "in_country",
        "entity": "France"
      }
    ]
  },
  {
    "value": "Primeira Liga",
    "categories": ["football-league"],
    "entityRelationships": [
      {
        "relation_type": "in_country",
        "entity": "Portugal"
      }
    ]
  },
  {
    "value": "Eredivisie",
    "categories": ["football-league"],
    "entityRelationships": [
      {
        "relation_type": "in_country",
        "entity": "Netherlands"
      }
    ]
  }
]
